minui/__init__.py
minui/__main__.py
minui/cli.py
minui/web.py
minui/core/__init__.py
minui/core/context.py
minui/core/llm.py
minui/static/favicon.ico
minui/static/css/style.css
minui/static/js/app.js
minui/templates/index.html
minui-0.1.0.dist-info/licenses/LICENSE
minui-0.1.0.dist-info/METADATA
minui-0.1.0.dist-info/WHEEL
minui-0.1.0.dist-info/entry_points.txt
minui-0.1.0.dist-info/top_level.txt
minui-0.1.0.dist-info/RECORD
