Metadata-Version: 2.4
Name: minui
Version: 0.1.0
Summary: LLM code review tool
Author-email: Igor <igor-alexey@hotmail.com>
License-Expression: GPL-2.0
Project-URL: Homepage, https://github.com/IgorAlexey/minui
Classifier: Programming Language :: Python :: 3
Classifier: Programming Language :: Python :: 3.8
Classifier: Programming Language :: Python :: 3.10
Classifier: Programming Language :: Python :: 3.11
Classifier: Programming Language :: Python :: 3.9
Classifier: Programming Language :: Python :: 3.12
Classifier: Operating System :: OS Independent
Requires-Python: >=3.8
License-File: LICENSE
Requires-Dist: flask>=3.0.0
Requires-Dist: requests>=2.31.0
Requires-Dist: pathspec>=0.11.0
Requires-Dist: waitress>=3.0.0
Dynamic: license-file
